kinglet/__init__.py
kinglet/authz.py
kinglet/cache_d1.py
kinglet/constants.py
kinglet/core.py
kinglet/decorators.py
kinglet/exceptions.py
kinglet/http.py
kinglet/kinglet.py
kinglet/middleware.py
kinglet/openapi.py
kinglet/orm.py
kinglet/orm_deploy.py
kinglet/orm_errors.py
kinglet/orm_migrations.py
kinglet/pagination.py
kinglet/serializers.py
kinglet/services.py
kinglet/ses.py
kinglet/sql.py
kinglet/storage.py
kinglet/testing.py
kinglet/totp.py
kinglet/utils.py
kinglet/validation.py
kinglet-1.8.3.dist-info/licenses/LICENSE
kinglet-1.8.3.dist-info/METADATA
kinglet-1.8.3.dist-info/WHEEL
kinglet-1.8.3.dist-info/entry_points.txt
kinglet-1.8.3.dist-info/top_level.txt
kinglet-1.8.3.dist-info/RECORD
