Metadata-Version: 2.4
Name: kinglet
Version: 1.8.3
Summary: A lightweight routing framework for Python Workers
Author-email: Mitchell Currie <mitchell@mitchins.dev>
License: MIT
Project-URL: Homepage, https://github.com/mitchins/Kinglet
Project-URL: Repository, https://github.com/mitchins/Kinglet
Project-URL: Bug Tracker, https://github.com/mitchins/Kinglet/issues
Keywords: cloudflare,workers,python,routing,web,framework,asgi,lightweight
Classifier: Development Status :: 5 - Production/Stable
Classifier: Intended Audience :: Developers
Classifier: License :: OSI Approved :: MIT License
Classifier: Operating System :: OS Independent
Classifier: Programming Language :: Python :: 3
Classifier: Programming Language :: Python :: 3.12
Classifier: Topic :: Internet :: WWW/HTTP :: HTTP Servers
Classifier: Topic :: Internet :: WWW/HTTP :: WSGI
Classifier: Topic :: Software Development :: Libraries :: Application Frameworks
Classifier: Topic :: Software Development :: Libraries :: Python Modules
Requires-Python: >=3.12
License-File: LICENSE
Provides-Extra: dev
Requires-Dist: pytest>=7.0; extra == "dev"
Requires-Dist: pytest-asyncio>=0.21; extra == "dev"
Requires-Dist: pytest-cov>=4.0; extra == "dev"
Requires-Dist: httpx>=0.27.0; extra == "dev"
Requires-Dist: ruff>=0.1.0; extra == "dev"
Requires-Dist: black>=22.0; extra == "dev"
Requires-Dist: mypy>=1.0; extra == "dev"
Requires-Dist: bandit>=1.7.0; extra == "dev"
Requires-Dist: safety>=2.0.0; extra == "dev"
Requires-Dist: pre-commit>=3.0.0; extra == "dev"
Provides-Extra: test
Requires-Dist: pytest>=7.0; extra == "test"
Requires-Dist: pytest-asyncio>=0.21; extra == "test"
Requires-Dist: pytest-cov>=4.0; extra == "test"
Requires-Dist: httpx>=0.27.0; extra == "test"
Requires-Dist: coverage>=6.0; extra == "test"
Dynamic: license-file
